coderz/__init__.py
coderz/ide.py
coderz/robot.py
coderz/utils.py
coderz/communication_managers/__init__.py
coderz/communication_managers/file.pem
coderz/communication_managers/ide_communication_manager.py
coderz/communication_managers/socket_communication_manager.py
examples/__init__.py
examples/move_robot.py
examples/read_sensor_values.py
examples/ws_move_robot.py
coderz-0.1.16.dist-info/LICENSE
coderz-0.1.16.dist-info/METADATA
coderz-0.1.16.dist-info/WHEEL
coderz-0.1.16.dist-info/top_level.txt
coderz-0.1.16.dist-info/RECORD
