Metadata-Version: 2.1
Name: coderz
Version: 0.1.16
Summary: CoderZ External IDE Tool
Home-page: https://github.com/go-coderz/coderz-python
Author: CoderZ
Author-email: app@gocoderz.com
License: UNKNOWN
Platform: UNKNOWN
Classifier: Programming Language :: Python :: 3
Classifier: License :: OSI Approved :: MIT License
Classifier: Operating System :: OS Independent
Requires-Python: >3.0
Requires-Dist: aiohttp (>=3.0.0)
Requires-Dist: python-socketio (==4.0.2)
Requires-Dist: requests (>=2.22.0)
Requires-Dist: websockets (>=7.0)
